mmdiary/__init__.py
mmdiary/notion/__init__.py
mmdiary/notion/cache.py
mmdiary/notion/cachedb.py
mmdiary/notion/cleanup.py
mmdiary/notion/uploader.py
mmdiary/telegrambot/__init__.py
mmdiary/telegrambot/telegrambot_service.py
mmdiary/transcriber/__init__.py
mmdiary/transcriber/searcher.py
mmdiary/transcriber/transcriber.py
mmdiary/transcriber/verifier.py
mmdiary/utils/__init__.py
mmdiary/utils/datelib.py
mmdiary/utils/jsoncache.py
mmdiary/utils/log.py
mmdiary/utils/medialib.py
mmdiary/utils/progressbar.py
mmdiary/utils/proxypatch.py
mmdiary/video/__init__.py
mmdiary/video/processor.py
mmdiary/video/uploader.py
mmdiary/video/uploader/__init__.py
mmdiary/video/uploader/common.py
mmdiary/video/uploader/dailymotion.py
mmdiary/video/uploader/youtube.py
mmdiary-0.4.0.dist-info/LICENSE
mmdiary-0.4.0.dist-info/METADATA
mmdiary-0.4.0.dist-info/WHEEL
mmdiary-0.4.0.dist-info/entry_points.txt
mmdiary-0.4.0.dist-info/top_level.txt
mmdiary-0.4.0.dist-info/RECORD
