Metadata-Version: 2.1
Name: mmdiary
Version: 0.4.0
Summary: Multimedia Diary Tools
Author-email: Alexander Bushnev <Alexander@Bushnev.pro>
Maintainer-email: Alexander Bushnev <Alexander@Bushnev.pro>
License: GNU GENERAL PUBLIC LICENSE
Project-URL: Homepage, https://github.com/sashacmc/mmdiary
Project-URL: Bug Reports, https://github.com/sashacmc/mmdiary/issues
Project-URL: Source, https://github.com/sashacmc/mmdiary/
Project-URL: Changelog, https://github.com/sashacmc/mmdiary/blob/master/CHANGELOG.md
Keywords: audio,video,multimedia,tool,youtube,notion,transcriber,uploader
Classifier: Development Status :: 4 - Beta
Classifier: Operating System :: POSIX :: Linux
Classifier: Operating System :: MacOS
Classifier: Programming Language :: Python
Classifier: Programming Language :: Python :: 3
Classifier: Programming Language :: Python :: 3.6
Classifier: Programming Language :: Python :: 3.7
Classifier: Programming Language :: Python :: 3.8
Classifier: Programming Language :: Python :: 3.9
Classifier: Programming Language :: Python :: 3.10
Classifier: Programming Language :: Python :: 3.11
Classifier: License :: OSI Approved :: GNU General Public License v3 or later (GPLv3+)
Classifier: Topic :: Multimedia :: Video
Classifier: Topic :: Utilities
Requires-Python: >=3.8
License-File: LICENSE
Requires-Dist: pytest
Requires-Dist: notion-client
Requires-Dist: notion
Requires-Dist: progressbar2
Requires-Dist: python-telegram-bot
Requires-Dist: openai-whisper
Requires-Dist: photo-importer
Requires-Dist: mixvideoconcat
Requires-Dist: dailymotion
Requires-Dist: free-proxy
Requires-Dist: google-auth-oauthlib
Requires-Dist: google-api-python-client
